teia_sdk/__init__.py
teia_sdk/__main__.py
teia_sdk/exceptions.py
teia_sdk/utils.py
teia_sdk/dbsailor/__init__.py
teia_sdk/dbsailor/client.py
teia_sdk/dbsailor/schemas.py
teia_sdk/melting/__init__.py
teia_sdk/melting/chat_prompts.py
teia_sdk/melting/client.py
teia_sdk/melting/schemas.py
teia_sdk/melting/services/__init__.py
teia_sdk/melting/services/chat_completions.py
teia_sdk/melting/services/chat_prompts.py
teia_sdk/melting/services/fcall_completions.py
teia_sdk/melting/services/tcall_completions.py
teia_sdk/melting/services/text_encodings.py
teia_sdk/plugins/__init__.py
teia_sdk/plugins/client.py
teia_sdk/plugins/exceptions.py
teia_sdk/plugins/plugins.py
teia_sdk/plugins/schemas.py
teia_sdk/private_workspaces/__init__.py
teia_sdk/private_workspaces/client.py
teia_sdk/private_workspaces/exceptions.py
teia_sdk/private_workspaces/private_workspaces.py
teia_sdk/private_workspaces/schemas.py
teia_sdk/search/__init__.py
teia_sdk/search/client.py
teia_sdk/search/schemas.py
teia_sdk/search/search.py
tests/__init__.py
tests/test_plugins.py
tests/test_search.py
teia_sdk-0.1.12.dist-info/METADATA
teia_sdk-0.1.12.dist-info/WHEEL
teia_sdk-0.1.12.dist-info/entry_points.txt
teia_sdk-0.1.12.dist-info/top_level.txt
teia_sdk-0.1.12.dist-info/RECORD
