Metadata-Version: 2.1
Name: teia_sdk
Version: 0.1.12
Summary: Teia SDK
Home-page: https://github.com/TeiaLabs/teia-sdk
Author: TeiaLabs
Author-email: contato@teialabs.com
Requires-Python: >=3.11
Requires-Dist: fastapi
Requires-Dist: http-error-schemas
Requires-Dist: melting-schemas ==1.0.13
Requires-Dist: httpx
Requires-Dist: python-dotenv
Requires-Dist: requests
Requires-Dist: rich
Requires-Dist: typer[all]
Provides-Extra: test
Requires-Dist: pytest ; extra == 'test'
